guangning_compare/__init__.py
guangning_compare/__main__.py
guangning_compare/comment/check_element.py
guangning_compare/comment/check_excle_last.py
guangning_compare/comment/check_existing_data.py
guangning_compare/comment/daoq.py
guangning_compare/comment/envWrite.py
guangning_compare/comment/excle_create.py
guangning_compare/comment/excle_write.py
guangning_compare/comment/file_create.py
guangning_compare/comment/floder_create.py
guangning_compare/comment/id_Verification.py
guangning_compare/comment/is_iso_8601.py
guangning_compare/comment/jdpd.py
guangning_compare/comment/logger.py
guangning_compare/comment/login_account.py
guangning_compare/comment/lz.py
guangning_compare/comment/phone_Verification.py
guangning_compare/comment/rqbaoc.py
guangning_compare/comment/write_excle.py
guangning_compare/comment/登录头.py
guangning_compare/compare.py
guangning_compare/compements/assemblies/check_diseases.py
guangning_compare/compements/assemblies/check_sf_date.py
guangning_compare/compements/assemblies/check_sf_date_same_day.py
guangning_compare/compements/assemblies/get_mb_data.py
guangning_compare/compements/assemblies/get_mz_data.py
guangning_compare/compements/assemblies/get_mz_time.py
guangning_compare/compements/assemblies/get_new_sf_data.py
guangning_compare/compements/assemblies/get_new_sf_date.py
guangning_compare/compements/assemblies/get_sf_data.py
guangning_compare/compements/assemblies/get_tj_data.py
guangning_compare/compements/assemblies/has_current_quarter.py
guangning_compare/compements/assemblies/introducing_medication.py
guangning_compare/compements/new_assessment.py
guangning_compare/compements/quarterly_statistics.py
guangning_compare/compements/tool.py
guangning_compare/compements/whether_assessment.py
guangning_compare/广宁慢病随访新建-重制最新版.py
guangning_compare-2025.8.19.0.dist-info/WHEEL
guangning_compare-2025.8.19.0.dist-info/entry_points.txt
guangning_compare-2025.8.19.0.dist-info/METADATA
guangning_compare-2025.8.19.0.dist-info/RECORD
