Metadata-Version: 2.3
Name: guangning-compare
Version: 2025.8.19.0
Summary: compare current source with guangning
Author: Maple
Author-email: Maple <wjxa20152015@gmail.com>
Requires-Python: >=3.8
